AUTHORS
LICENCE
MANIFEST.in
README.md
setup.py
salebox_django.egg-info/PKG-INFO
salebox_django.egg-info/SOURCES.txt
salebox_django.egg-info/dependency_links.txt
salebox_django.egg-info/not-zip-safe
salebox_django.egg-info/requires.txt
salebox_django.egg-info/top_level.txt
saleboxdjango/__init__.py
saleboxdjango/admin.py
saleboxdjango/apps.py
saleboxdjango/context_processor.py
saleboxdjango/forms.py
saleboxdjango/middleware.py
saleboxdjango/models.py
saleboxdjango/urls.py
saleboxdjango/lib/__init__.py
saleboxdjango/lib/address.py
saleboxdjango/lib/api.py
saleboxdjango/lib/basket.py
saleboxdjango/lib/binpack.py
saleboxdjango/lib/category.py
saleboxdjango/lib/checkout.py
saleboxdjango/lib/common.py
saleboxdjango/lib/event_handler.py
saleboxdjango/lib/product.py
saleboxdjango/lib/rating.py
saleboxdjango/lib/shipping_options.py
saleboxdjango/lib/translation.py
saleboxdjango/lib/variant.py
saleboxdjango/locale/th/LC_MESSAGES/django.mo
saleboxdjango/locale/th/LC_MESSAGES/django.po
saleboxdjango/management/__init__.py
saleboxdjango/management/commands/__init__.py
saleboxdjango/management/commands/saleboxcleanup.py
saleboxdjango/management/commands/saleboxsync.py
saleboxdjango/management/commands/saleboxsync2.py
saleboxdjango/management/commands/lib/__init__.py
saleboxdjango/management/commands/lib/log.py
saleboxdjango/management/commands/lib/sync_pull_inventory.py
saleboxdjango/management/commands/lib/sync_pull_models.py
saleboxdjango/management/commands/lib/sync_pull_posimages.py
saleboxdjango/management/commands/lib/sync_pull_queue.py
saleboxdjango/management/commands/lib/sync_push_footfall.py
saleboxdjango/management/commands/lib/models/__init__.py
saleboxdjango/management/commands/lib/models/contentkeyvaluestore.py
saleboxdjango/management/commands/lib/models/contentpage.py
saleboxdjango/management/commands/lib/models/contentpageitem.py
saleboxdjango/management/commands/lib/models/product.py
saleboxdjango/management/commands/lib/models/productcategory.py
saleboxdjango/management/commands/lib/models/productvariant.py
saleboxdjango/migrations/0001_initial.py
saleboxdjango/migrations/0002_auto_20190813_1349.py
saleboxdjango/migrations/0003_auto_20190827_0809.py
