Metadata-Version: 2.1
Name: salebox-django
Version: 0.0.264
Summary: Django ecommerce powered by Salebox
Home-page: https://salebox.io
Author: Jon Combe
Author-email: jon@salebox.io
License: BSD licence, see LICENCE file
Classifier: Development Status :: 3 - Alpha
Classifier: Environment :: Web Environment
Classifier: Framework :: Django
Classifier: Intended Audience :: Developers
Classifier: License :: OSI Approved :: BSD License
Classifier: Natural Language :: English
Classifier: Operating System :: OS Independent
Classifier: Programming Language :: Python
License-File: LICENCE
License-File: AUTHORS
Requires-Dist: django-json-widget
Requires-Dist: django-mptt
Requires-Dist: django-opposable-thumbs
Requires-Dist: geoip2
Requires-Dist: pyShipping-python3
Requires-Dist: pyyaml
Requires-Dist: requests
Requires-Dist: ua-parser
Requires-Dist: user-agents
